pytest_frappe/__init__.py
pytest_frappe/fixtures.py
pytest_frappe/plugin.py
pytest_frappe-0.2.5.dist-info/entry_points.txt
pytest_frappe-0.2.5.dist-info/LICENSE
pytest_frappe-0.2.5.dist-info/WHEEL
pytest_frappe-0.2.5.dist-info/METADATA
pytest_frappe-0.2.5.dist-info/RECORD
